{
    "vpx_ami_map": {
        "ap-northeast-1": "ami-01194b1361389eb8d",
        "ap-northeast-2": "ami-0dbaf51d4d2de6442",
        "ap-south-1": "ami-05244cfefe2d6cfaa",
        "ap-southeast-1": "ami-01fca73bac92936da",
        "ap-southeast-2": "ami-0f9bf027890ea2758",
        "ca-central-1": "ami-0b3004b2677105309",
        "eu-central-1": "ami-067eb93f9f2512bca",
        "eu-west-1": "ami-026c662d166a96d2d",
        "eu-west-2": "ami-05e5c228b48570d22",
        "sa-east-1": "ami-0f8fcc40a0cf432e0",
        "us-east-1": "ami-0d7e176b61cb877f0",
        "us-east-2": "ami-0f50fbade2657c721",
        "us-west-1": "ami-0d23a7f21e76914b1",
        "us-west-2": "ami-08ca51fb4bcdf7a46"
    }
}